odoo/addons/stock_dynamic_routing_reserve_rule/README.rst
odoo/addons/stock_dynamic_routing_reserve_rule/__init__.py
odoo/addons/stock_dynamic_routing_reserve_rule/__manifest__.py
odoo/addons/stock_dynamic_routing_reserve_rule/i18n/es_AR.po
odoo/addons/stock_dynamic_routing_reserve_rule/i18n/stock_dynamic_routing_reserve_rule.pot
odoo/addons/stock_dynamic_routing_reserve_rule/models/__init__.py
odoo/addons/stock_dynamic_routing_reserve_rule/models/stock_routing.py
odoo/addons/stock_dynamic_routing_reserve_rule/readme/DESCRIPTION.rst
odoo/addons/stock_dynamic_routing_reserve_rule/static/description/icon.png
odoo/addons/stock_dynamic_routing_reserve_rule/static/description/index.html
odoo/addons/stock_dynamic_routing_reserve_rule/templates/stock_routing_templates.xml
odoo/addons/stock_dynamic_routing_reserve_rule/views/stock_routing_views.xml
odoo14_addon_stock_dynamic_routing_reserve_rule-14.0.1.0.1.dist-info/METADATA
odoo14_addon_stock_dynamic_routing_reserve_rule-14.0.1.0.1.dist-info/WHEEL
odoo14_addon_stock_dynamic_routing_reserve_rule-14.0.1.0.1.dist-info/top_level.txt
odoo14_addon_stock_dynamic_routing_reserve_rule-14.0.1.0.1.dist-info/RECORD
